{
  "ts": "2026-04-12T09:03:01.270700+09:00",
  "start_date": "2026-04-05",
  "status": "running",
  "equity": 114858.85,
  "available": 95392.65,
  "unrealized": -164.48,
  "daily_pnl": -104.21,
  "total_pnl": 9858.85,
  "cum_pct": 9.39,
  "daily_avg_pct": 1.1738,
  "annual_pct": 6976.89,
  "mdd": -2.22,
  "current_dd": -0.45,
  "seed_used": 19466.2,
  "seed_used_pct": 16.95,
  "long_count": 6,
  "short_count": 6,
  "positions": [
    {
      "symbol": "SOLUSDT",
      "side": "SHORT",
      "pnl": -196.18,
      "pnl_pct": -0.54,
      "margin": 4001.56,
      "leverage": "9",
      "tier": "7/9",
      "entry": 84.4012,
      "mark": 84.861
    },
    {
      "symbol": "BNBUSDT",
      "side": "SHORT",
      "pnl": -18.82,
      "pnl_pct": -0.11,
      "margin": 1895.84,
      "leverage": "9",
      "tier": "4/9",
      "entry": 606.1313,
      "mark": 606.8
    },
    {
      "symbol": "LTCUSDT",
      "side": "SHORT",
      "pnl": -19.71,
      "pnl_pct": -0.16,
      "margin": 1534.38,
      "leverage": "8",
      "tier": "3/9",
      "entry": 54.9218,
      "mark": 55.01
    },
    {
      "symbol": "DOGEUSDT",
      "side": "LONG",
      "pnl": -34.77,
      "pnl_pct": -0.25,
      "margin": 1408.93,
      "leverage": "10",
      "tier": "4/9",
      "entry": 0.0932,
      "mark": 0.0929
    },
    {
      "symbol": "BCHUSDT",
      "side": "SHORT",
      "pnl": 117.47,
      "pnl_pct": 1.06,
      "margin": 1389.76,
      "leverage": "8",
      "tier": "4/9",
      "entry": 442.0709,
      "mark": 437.4
    },
    {
      "symbol": "AVAXUSDT",
      "side": "SHORT",
      "pnl": -31.83,
      "pnl_pct": -0.38,
      "margin": 834.41,
      "leverage": "10",
      "tier": "2/9",
      "entry": 9.3334,
      "mark": 9.369
    },
    {
      "symbol": "XRPUSDT",
      "side": "LONG",
      "pnl": -8.21,
      "pnl_pct": -0.13,
      "margin": 767.98,
      "leverage": "8",
      "tier": "3/9",
      "entry": 1.356,
      "mark": 1.3542
    },
    {
      "symbol": "DOTUSDT",
      "side": "SHORT",
      "pnl": 41.13,
      "pnl_pct": 0.61,
      "margin": 675.89,
      "leverage": "10",
      "tier": "3/9",
      "entry": 1.2939,
      "mark": 1.286
    },
    {
      "symbol": "WLDUSDT",
      "side": "LONG",
      "pnl": -30.23,
      "pnl_pct": -0.72,
      "margin": 469.13,
      "leverage": "9",
      "tier": "3/11",
      "entry": 0.298,
      "mark": 0.2959
    },
    {
      "symbol": "BTCUSDT",
      "side": "LONG",
      "pnl": 16.58,
      "pnl_pct": 0.39,
      "margin": 421.37,
      "leverage": "10",
      "tier": "2/9",
      "entry": 72649.3,
      "mark": 72935.22
    },
    {
      "symbol": "SUIUSDT",
      "side": "LONG",
      "pnl": -4.11,
      "pnl_pct": -0.16,
      "margin": 291.07,
      "leverage": "9",
      "tier": "2/9",
      "entry": 0.9423,
      "mark": 0.9408
    },
    {
      "symbol": "HYPEUSDT",
      "side": "LONG",
      "pnl": 4.27,
      "pnl_pct": 0.21,
      "margin": 250.19,
      "leverage": "8",
      "tier": "2/10",
      "entry": 42.208,
      "mark": 42.298
    }
  ],
  "signals": {
    "LINKUSDT": {
      "dir": "short",
      "conf": 0.529
    },
    "DOGEUSDT": {
      "dir": "long",
      "conf": 0.639
    },
    "NEARUSDT": {
      "dir": "short",
      "conf": 0.504
    },
    "BTCUSDT": {
      "dir": "long",
      "conf": 0.905
    },
    "TRUMPUSDT": {
      "dir": "short",
      "conf": 0.569
    },
    "AAVEUSDT": {
      "dir": "long",
      "conf": 0.518
    },
    "AVAXUSDT": {
      "dir": "long",
      "conf": 0.522
    },
    "ETHUSDT": {
      "dir": "short",
      "conf": 0.529
    },
    "ZECUSDT": {
      "dir": "long",
      "conf": 0.503
    },
    "BNBUSDT": {
      "dir": "long",
      "conf": 0.522
    },
    "ALGOUSDT": {
      "dir": "short",
      "conf": 0.529
    },
    "HYPEUSDT": {
      "dir": "long",
      "conf": 0.599
    },
    "SUIUSDT": {
      "dir": "long",
      "conf": 0.716
    },
    "SOLUSDT": {
      "dir": "long",
      "conf": 0.668
    },
    "XRPUSDT": {
      "dir": "long",
      "conf": 0.506
    },
    "DOTUSDT": {
      "dir": "long",
      "conf": 0.532
    },
    "1000PEPEUSDT": {
      "dir": "short",
      "conf": 0.51
    },
    "ENAUSDT": {
      "dir": "long",
      "conf": 0.55
    },
    "ADAUSDT": {
      "dir": "long",
      "conf": 0.626
    },
    "TAOUSDT": {
      "dir": "short",
      "conf": 0.715
    },
    "WLDUSDT": {
      "dir": "long",
      "conf": 0.681
    },
    "BCHUSDT": {
      "dir": "long",
      "conf": 0.703
    },
    "LTCUSDT": {
      "dir": "short",
      "conf": 0.611
    },
    "XMRUSDT": {
      "dir": "short",
      "conf": 0.562
    },
    "ARBUSDT": {
      "dir": "short",
      "conf": 0.506
    },
    "TONUSDT": {
      "dir": "long",
      "conf": 0.528
    },
    "WLFIUSDT": {
      "dir": "short",
      "conf": 0.503
    },
    "DASHUSDT": {
      "dir": "long",
      "conf": 0.543
    }
  },
  "equity_hist": [
    {
      "t": "2026-04-05",
      "v": 86.05
    },
    {
      "t": "2026-04-06",
      "v": 141.8
    },
    {
      "t": "2026-04-07",
      "v": -467.37
    },
    {
      "t": "2026-04-08",
      "v": -1158.16
    },
    {
      "t": "2026-04-09",
      "v": -980.49
    },
    {
      "t": "2026-04-10",
      "v": -817.12
    },
    {
      "t": "2026-04-11",
      "v": -920.37
    },
    {
      "t": "2026-04-12",
      "v": -1054.27
    }
  ],
  "trade_history": [
    {
      "ts": "2026-04-12 08:09",
      "symbol": "SUIUSDT",
      "side": "Buy",
      "pnl": -82.76,
      "reason": "3/9"
    },
    {
      "ts": "2026-04-12 07:57",
      "symbol": "ADAUSDT",
      "side": "Sell",
      "pnl": 24.03,
      "reason": "4/9"
    },
    {
      "ts": "2026-04-12 07:39",
      "symbol": "WLDUSDT",
      "side": "Buy",
      "pnl": 2.5,
      "reason": "1/11"
    },
    {
      "ts": "2026-04-12 06:24",
      "symbol": "WLDUSDT",
      "side": "Buy",
      "pnl": -0.0,
      "reason": "5/9"
    },
    {
      "ts": "2026-04-12 06:24",
      "symbol": "ADAUSDT",
      "side": "Sell",
      "pnl": -9.15,
      "reason": "5/9"
    },
    {
      "ts": "2026-04-12 06:22",
      "symbol": "WLDUSDT",
      "side": "Buy",
      "pnl": -0.02,
      "reason": "1/12"
    },
    {
      "ts": "2026-04-12 06:21",
      "symbol": "WLDUSDT",
      "side": "Buy",
      "pnl": 0.65,
      "reason": "-"
    },
    {
      "ts": "2026-04-12 06:02",
      "symbol": "SUIUSDT",
      "side": "Sell",
      "pnl": -71.2,
      "reason": "3/9"
    },
    {
      "ts": "2026-04-12 05:46",
      "symbol": "SUIUSDT",
      "side": "Sell",
      "pnl": -94.48,
      "reason": "4/9"
    },
    {
      "ts": "2026-04-12 05:31",
      "symbol": "DOTUSDT",
      "side": "Buy",
      "pnl": 27.5,
      "reason": "1/9"
    },
    {
      "ts": "2026-04-12 04:42",
      "symbol": "WLDUSDT",
      "side": "Buy",
      "pnl": 0.0,
      "reason": "L2"
    },
    {
      "ts": "2026-04-12 04:38",
      "symbol": "WLDUSDT",
      "side": "Buy",
      "pnl": 31.82,
      "reason": "1/11"
    },
    {
      "ts": "2026-04-12 03:59",
      "symbol": "WLDUSDT",
      "side": "Buy",
      "pnl": 29.05,
      "reason": "-"
    },
    {
      "ts": "2026-04-12 01:39",
      "symbol": "WLDUSDT",
      "side": "Buy",
      "pnl": 0.0,
      "reason": "L2"
    },
    {
      "ts": "2026-04-12 01:36",
      "symbol": "WLDUSDT",
      "side": "Buy",
      "pnl": 60.9,
      "reason": "1/10"
    },
    {
      "ts": "2026-04-12 01:15",
      "symbol": "AAVEUSDT",
      "side": "Sell",
      "pnl": -23.04,
      "reason": "2/9"
    },
    {
      "ts": "2026-04-11 23:10",
      "symbol": "WLDUSDT",
      "side": "Buy",
      "pnl": 31.98,
      "reason": "-"
    },
    {
      "ts": "2026-04-11 22:02",
      "symbol": "WLDUSDT",
      "side": "Buy",
      "pnl": -0.0,
      "reason": "L2"
    },
    {
      "ts": "2026-04-11 22:00",
      "symbol": "WLDUSDT",
      "side": "Buy",
      "pnl": -96.22,
      "reason": "3/11"
    },
    {
      "ts": "2026-04-11 18:42",
      "symbol": "WLDUSDT",
      "side": "Buy",
      "pnl": 0.0,
      "reason": "L2"
    }
  ],
  "num_days": 8
}